starextractor/__init__.py
starextractor/classes.py
starextractor/image.py
starextractor/invariantfeatures.py
starextractor/plot.py
starextractor-0.2.0.dist-info/LICENSE
starextractor-0.2.0.dist-info/METADATA
starextractor-0.2.0.dist-info/WHEEL
starextractor-0.2.0.dist-info/top_level.txt
starextractor-0.2.0.dist-info/RECORD
