Metadata-Version: 2.1
Name: starextractor
Version: 0.2.0
Summary: A package for extracting stars and doing photometry from an astronomical image
Home-page: https://github.com/lcx366/STAREXTRACTOR
Author: Chunxiao Li
Author-email: lcx366@126.com
License: MIT
Keywords: source extraction,photometry,psf,daofind,fwhm
Classifier: Development Status :: 4 - Beta
Classifier: Intended Audience :: Education
Classifier: Intended Audience :: Science/Research
Classifier: Programming Language :: Python :: 3.10
Classifier: Programming Language :: Python :: 3.11
Classifier: Programming Language :: Python :: 3.12
Classifier: License :: OSI Approved :: MIT License
Requires-Python: >=3.10
License-File: LICENSE
Requires-Dist: photutils
Requires-Dist: astropy (>=4.3.1)
Requires-Dist: Pillow
Requires-Dist: scipy
Requires-Dist: matplotlib
